django_cotton_components/__init__.py
django_cotton_components/apps.py
django_cotton_components/tests.py
django_cotton_components/templates/cotton/dcc_button.html
django_cotton_components/templates/cotton/dcc_checkbox.html
django_cotton_components/templates/cotton/dcc_h.html
django_cotton_components/templates/cotton/dcc_input.html
django_cotton_components/templates/cotton/dcc_modal.html
django_cotton_components/templates/cotton/dcc_radio.html
django_cotton_components/templates/cotton/dcc_select.html
django_cotton_components/templates/cotton/dcc_select_multiple.html
django_cotton_components/templates/cotton/dcc_table.html
django_cotton_components/templates/cotton/dcc_textarea.html
django_cotton_components/templates/cotton/dcc_toggle.html
django_cotton_components/templates/cotton/dcc_input/password.html
django_cotton_components/templatetags/__init__.py
django_cotton_components/templatetags/dcc_tags.py
django_cotton_components-0.1.6.dist-info/AUTHORS.MD
django_cotton_components-0.1.6.dist-info/LICENSE
django_cotton_components-0.1.6.dist-info/METADATA
django_cotton_components-0.1.6.dist-info/WHEEL
django_cotton_components-0.1.6.dist-info/top_level.txt
django_cotton_components-0.1.6.dist-info/RECORD
