Metadata-Version: 2.2
Name: django-cotton-components
Version: 0.1.6
Summary: A Django package with pre-built cotton-based UI components for rapid development.
Author-email: Sakaria Ndadi <oipapi.ndadi@gmail.com>
License: MIT License
Keywords: django,components,ui,cotton
Classifier: Development Status :: 3 - Alpha
Classifier: Intended Audience :: Developers
Classifier: Intended Audience :: Science/Research
Classifier: License :: OSI Approved :: MIT License
Classifier: Programming Language :: Python :: 3.12
Classifier: Framework :: Django
Requires-Python: >=3.8
License-File: LICENSE
License-File: AUTHORS.MD
Requires-Dist: build>=1.2.2.post1
Requires-Dist: django-cotton==1.5.1
Requires-Dist: twine>=6.1.0
